tokatami/__init__.py
tokatami/libtokatami.so
tokatami/wrapper.py
tokatami-0.0.1.dist-info/METADATA
tokatami-0.0.1.dist-info/WHEEL
tokatami-0.0.1.dist-info/RECORD
