Metadata-Version: 2.4
Name: tokatami
Version: 0.0.1
Summary: Python bindings for Tokatami
Requires-Python: >=3.10
